bifrons/__init__.py
bifrons/cli.py
bifrons/core.py
bifrons-1.1.0.dist-info/licenses/LICENSE
bifrons-1.1.0.dist-info/METADATA
bifrons-1.1.0.dist-info/WHEEL
bifrons-1.1.0.dist-info/entry_points.txt
bifrons-1.1.0.dist-info/top_level.txt
bifrons-1.1.0.dist-info/RECORD
