Metadata-Version: 2.4
Name: bifrons
Version: 1.1.0
Summary: SemVer automation CLI based on PR title
Author-email: Fernando Barreto <kalimbinhaa@gmail.com>
License-Expression: MIT
Requires-Python: >=3.8
License-File: LICENSE
Dynamic: license-file
